hubkit/__init__.py
hubkit/config.py
hubkit/tools/__init__.py
hubkit/tools/requestbin.py
hubkit-1.0.0.dist-info/METADATA
hubkit-1.0.0.dist-info/WHEEL
hubkit-1.0.0.dist-info/top_level.txt
hubkit-1.0.0.dist-info/RECORD
