Metadata-Version: 2.4
Name: hubkit
Version: 1.0.0
Summary: Add your description here
Requires-Python: >=3.12
Requires-Dist: requests>=2.32.4
Requires-Dist: websockets>=15.0.1
